{"id":"se.cambio::gel_diagnosis_query","version":"0.0.1","author":{"name":"Eneimi Allwell-Brown","email":"eneimi.allwell-brown@cambio.se"},"timestamp":"2022-01-13T19:41:47+01:00","body":"SELECT\n  a/data[at0001]/items[at0002]/value as T0_specific_disease,\n  a/data[at0001]/items[openEHR-EHR-CLUSTER.disease_group_rd_gel.v0]/items[at0001]/value as T0_disease_group,\n  a/data[at0001]/items[openEHR-EHR-CLUSTER.disease_group_rd_gel.v0]/items[at0002]/value as T0_disease_subgroup,\n  c/context/other_context/items[openEHR-EHR-CLUSTER.participant_gel.v0]/items[at0017]/value as T0_participant_type\nFROM\n  EHR e CONTAINS COMPOSITION c CONTAINS (\n    EVALUATION a[openEHR-EHR-EVALUATION.problem_diagnosis.v1]\n  )\nLIMIT\n  1\nORDER BY\n  c/context/start_time/value DESC","description":"","template":{"id":"GEL_diagnosis_report","version":"0.1.0"}}